atc_easy_desktop/__init__.py
atc_easy_desktop/atc_easy_desktop.py
atc_easy_desktop-1.0.5.dist-info/METADATA
atc_easy_desktop-1.0.5.dist-info/WHEEL
atc_easy_desktop-1.0.5.dist-info/top_level.txt
atc_easy_desktop-1.0.5.dist-info/RECORD
