Metadata-Version: 2.1
Name: atc-easy-desktop
Version: 1.0.5
Summary: Thư viện sử dụng để code game trên màn hình desktop
Home-page: UNKNOWN
Author: Chienbg200
Author-email: chienbg200400@gmail.com
License: UNKNOWN
Platform: UNKNOWN
Classifier: Programming Language :: Python
Classifier: Programming Language :: Python :: 3
Classifier: License :: OSI Approved :: MIT License
Classifier: Operating System :: Microsoft :: Windows
Classifier: Topic :: Software Development :: Libraries
Requires-Dist: pywin32
